multi_requests/__init__.py
multi_requests/py.typed
multi_requests-0.0.3.dist-info/LICENSE
multi_requests-0.0.3.dist-info/METADATA
multi_requests-0.0.3.dist-info/WHEEL
multi_requests-0.0.3.dist-info/top_level.txt
multi_requests-0.0.3.dist-info/RECORD
